unicategories/__init__.py
unicategories/database.pickle
unicategories_tools/__init__.py
unicategories_tools/cache.py
unicategories-0.1.0.dist-info/LICENSE
unicategories-0.1.0.dist-info/METADATA
unicategories-0.1.0.dist-info/WHEEL
unicategories-0.1.0.dist-info/top_level.txt
unicategories-0.1.0.dist-info/zip-safe
unicategories-0.1.0.dist-info/RECORD
