Metadata-Version: 2.1
Name: unicategories
Version: 0.1.0
Summary: Unicode category database
Home-page: https://gitlab.com/ergoithz/unicategories
Author: Felipe A. Hernandez
Author-email: ergoithz@gmail.com
License: MIT
Keywords: unicode
Platform: any
Classifier: License :: OSI Approved :: MIT License
Classifier: Operating System :: OS Independent
Classifier: Programming Language :: Python
Classifier: Programming Language :: Python :: 3
Requires-Dist: appdirs
